{
    "sen_info": {
        "main_info": {
            "_comentario": "Las fechas deben expresarse con guiones",
            "fecha": "23-08-2023",
            "dia": "Miercoles",
            "url": "http://www.cubadebate.cu/noticias/2023/08/23/une-no-pronostica-afectaciones-durante-pico-nocturno-de-este-miercoles/"
        },
        "_comentario": "Toda esta informacion se expresa en MW",
        "estimacion": {
            "horario": "noche",
            "disponibilidad": 3092,
            "demanda_max":2850,
            "deficit": 0,
            "pronostico": {
                "afectacion":0 
            }
        },
        "info_horarios": {
            "mañana": {
                "disponibilidad": 2664,
                "demanda": 2278,
                "totalidad": true
            },
            "mediodia": {
                "pronostico": {
                    "afectacion": 0
                }
            }
        },
        "termoelectricas": {
            "_comentario": "Esto quiere decir: Limitaciones en la generacion termica",
            "lim_gen_term": 428,
            "fuera": {
                "averias": [],
                "mantenimiento":[
                    {
                        "nombre": "Unidad 6",
                        "CTE": "Rente"
                    }
                ],
                "no_servicio": ""
            }
        },
        "pico": {
            "estimacion": [{
                "desc": "entrada de motores de generacion distribuida",
                "razon": "se encuentran fuera por combustible",
                "cantidad_mw": 462
            }]
        },
        "max_afect_dia": {
            "cantidad_mw": 0,
            "hora": "",
            "desc": ""
        },
        "dia_anterior": {
            "desc": "no hubo afecacion",
            "horas": "",
            "hora_rest": ""
        }
    }
}